cosmograph_widget/__about__.py
cosmograph_widget/__init__.py
cosmograph_widget/widget.py
cosmograph_widget/static/meta.json
cosmograph_widget/static/widget-GE5OCR2L.css
cosmograph_widget/static/widget-ZO2IYOSN.js
cosmograph_widget-0.0.3.dist-info/METADATA
cosmograph_widget-0.0.3.dist-info/WHEEL
cosmograph_widget-0.0.3.dist-info/licenses/LICENSE
cosmograph_widget-0.0.3.dist-info/RECORD
