Metadata-Version: 2.4
Name: cosmograph-widget
Version: 0.0.3
License-File: LICENSE
Requires-Dist: anywidget
Requires-Dist: pyarrow
Provides-Extra: dev
Requires-Dist: jupyterlab; extra == 'dev'
Requires-Dist: watchfiles; extra == 'dev'
